ptprssi/__init__.py
ptprssi/_version.py
ptprssi/ptprssi.py
ptprssi-1.0.5.dist-info/licenses/LICENSE
ptprssi-1.0.5.dist-info/METADATA
ptprssi-1.0.5.dist-info/WHEEL
ptprssi-1.0.5.dist-info/entry_points.txt
ptprssi-1.0.5.dist-info/top_level.txt
ptprssi-1.0.5.dist-info/RECORD
